asciinet/__init__.py
asciinet/__version__.py
asciinet/_libutil.py
asciinet/lib/asciigraph-assembly-0.2.1.jar
asciinet/test/__init__.py
asciinet/test/base.py
asciinet/test/test_ascii.py
asciinet-0.3.1.dist-info/LICENSE
asciinet-0.3.1.dist-info/METADATA
asciinet-0.3.1.dist-info/NOTICE
asciinet-0.3.1.dist-info/WHEEL
asciinet-0.3.1.dist-info/top_level.txt
asciinet-0.3.1.dist-info/RECORD
