Metadata-Version: 2.1
Name: asciinet
Version: 0.3.1
Summary: A wrapper around the scala ascii-graphs library
Home-page: UNKNOWN
Author: Cosmin Basca
Author-email: cosmin.basca@gmail.com
License: UNKNOWN
Platform: UNKNOWN
Classifier: Intended Audience :: Developers
Classifier: Natural Language :: English
Classifier: Operating System :: OS Independent
Classifier: Programming Language :: Python
Classifier: Programming Language :: Java
Classifier: Topic :: Software Development
License-File: LICENSE
License-File: NOTICE
Requires-Dist: networkx (>=1.9)
Requires-Dist: natsort (>=3.2.0)
Requires-Dist: requests (>=2.3.0)
Requires-Dist: msgpack-python (>=0.4.2)
